LICENSE
atomkraft/__init__.py
atomkraft/__main__.py
atomkraft/_version.py
atomkraft/chain/__init__.py
atomkraft/chain/node.py
atomkraft/chain/pytest.py
atomkraft/chain/testnet.py
atomkraft/chain/utils.py
atomkraft/cli/__init__.py
atomkraft/config/atomkraft_config.py
atomkraft/config/chain_config.py
atomkraft/config/config_file.py
atomkraft/config/model_config.py
atomkraft/model/traces.py
atomkraft/reactor/constants.py
atomkraft/reactor/reactor.py
atomkraft/reactor/step_functions_visitor.py
atomkraft/reactor/utils.py
atomkraft/templates/project/.atomkraft/config.toml
atomkraft/templates/project/.atomkraft/smoke_tests/.gitkeep
atomkraft/templates/project/.modelator/.gitkeep
atomkraft/templates/project/atomkraft.toml
atomkraft/templates/project/chain.toml
atomkraft/templates/project/model.toml
atomkraft/templates/project/models/.gitkeep
atomkraft/templates/project/pyproject.toml
atomkraft/templates/project/pytest.ini
atomkraft/templates/project/reactors/.gitkeep
atomkraft/templates/project/reports/.gitkeep
atomkraft/templates/project/tests/.gitkeep
atomkraft/templates/project/traces/.gitkeep
atomkraft/test/__init__.py
atomkraft/test/model.py
atomkraft/test/test.py
atomkraft/test/trace.py
atomkraft/utils/__init__.py
atomkraft/utils/filesystem.py
atomkraft/utils/helpers.py
atomkraft/utils/project.py
atomkraft-0.1.2.dist-info/entry_points.txt
atomkraft-0.1.2.dist-info/LICENSE
atomkraft-0.1.2.dist-info/WHEEL
atomkraft-0.1.2.dist-info/METADATA
atomkraft-0.1.2.dist-info/RECORD
