Metadata-Version: 2.1
Name: atomkraft
Version: 0.1.2
Summary: Testing for Cosmos Blockchains
Home-page: https://github.com/informalsystems/atomkraft
License: Apache-2.0
Keywords: cosmos,blockchain,testing,testnet
Author: Andrey Kuprianov
Author-email: andrey@informal.systems
Requires-Python: >=3.8,<4.0
Classifier: License :: OSI Approved :: Apache Software License
Classifier: Programming Language :: Python :: 3
Classifier: Programming Language :: Python :: 3.8
Classifier: Programming Language :: Python :: 3.9
Classifier: Programming Language :: Python :: 3.10
Classifier: Programming Language :: Python :: 3.11
Classifier: Programming Language :: Python :: 3 :: Only
Classifier: Topic :: Software Development :: Testing
Requires-Dist: bip-utils (>=2.7.0,<3.0.0)
Requires-Dist: case-converter (>=1.1.0,<2.0.0)
Requires-Dist: hdwallet (>=2.1.2,<3.0.0)
Requires-Dist: jinja2 (>=3.1.2,<4.0.0)
Requires-Dist: jsonrpcclient (>=4.0.2,<5.0.0)
Requires-Dist: modelator (>=0.6.6,<0.7.0)
Requires-Dist: numpy (>=1.23.4,<2.0.0)
Requires-Dist: pytest (>=7.2.0,<8.0.0)
Requires-Dist: pytest-reportlog (>=0.1.2,<0.2.0)
Requires-Dist: rich (>=12.6.0,<13.0.0)
Requires-Dist: setuptools (>=65.5.1,<66.0.0)
Requires-Dist: tabulate (>=0.9.0,<0.10.0)
Requires-Dist: tenacity (>=8.1.0,<9.0.0)
Requires-Dist: terra-proto (>=2.1.0,<3.0.0)
Requires-Dist: terra-sdk (>=3.0.1,<4.0.0)
Requires-Dist: tomlkit (>=0.11.6,<0.12.0)
Requires-Dist: typer[all] (>=0.7.0,<0.8.0)
Requires-Dist: websockets (>=10.4,<11.0)
Project-URL: Repository, https://github.com/informalsystems/atomkraft
